tests/__init__.py
tests/test_functions.py
ecs_manager/functions.py
ecs_manager/cmd.py
ecs_manager/__init__.py
ecs_manager/utils/__init__.py
ecs_manager/utils/json_util.py
ecs_manager-0.1.5.0.dist-info/RECORD
ecs_manager-0.1.5.0.dist-info/metadata.json
ecs_manager-0.1.5.0.dist-info/WHEEL
ecs_manager-0.1.5.0.dist-info/entry_points.txt
ecs_manager-0.1.5.0.dist-info/DESCRIPTION.rst
ecs_manager-0.1.5.0.dist-info/top_level.txt
ecs_manager-0.1.5.0.dist-info/METADATA
