Metadata-Version: 2.0
Name: ecs-manager
Version: 0.1.5.0
Summary: Manage ecs service
Home-page: https://github.com/pistatium/ecs_service_manager
Author: pistatium
Author-email: UNKNOWN
License: UNKNOWN
Platform: UNKNOWN
Requires-Dist: boto3
Requires-Dist: click
Requires-Dist: future
